paref/__init__.py
paref/blackbox_functions/__init__.py
paref/blackbox_functions/design_space/__init__.py
paref/blackbox_functions/design_space/bounds.py
paref/express/__init__.py
paref/express/express_search.py
paref/express/info.py
paref/interfaces/__init__.py
paref/interfaces/decorators.py
paref/interfaces/moo_algorithms/__init__.py
paref/interfaces/moo_algorithms/blackbox_function.py
paref/interfaces/moo_algorithms/paref_moo.py
paref/interfaces/moo_algorithms/stopping_criteria.py
paref/interfaces/pareto_reflections/__init__.py
paref/interfaces/pareto_reflections/pareto_reflection.py
paref/interfaces/sequences_pareto_reflections/__init__.py
paref/interfaces/sequences_pareto_reflections/sequence_pareto_reflections.py
paref/moo_algorithms/__init__.py
paref/moo_algorithms/minimizer/__init__.py
paref/moo_algorithms/minimizer/differential_evolution_minimizer.py
paref/moo_algorithms/minimizer/gpr_minimizer.py
paref/moo_algorithms/minimizer/surrogates/__init__.py
paref/moo_algorithms/minimizer/surrogates/gpr.py
paref/moo_algorithms/minimizer/surrogates/preprocessing.py
paref/moo_algorithms/multi_dimensional/__init__.py
paref/moo_algorithms/multi_dimensional/find_1_pareto_points.py
paref/moo_algorithms/multi_dimensional/find_edge_points.py
paref/moo_algorithms/multi_dimensional/min_g.py
paref/moo_algorithms/stopping_criteria/__init__.py
paref/moo_algorithms/stopping_criteria/convergence_reached.py
paref/moo_algorithms/stopping_criteria/logical_or_stopping_criteria.py
paref/moo_algorithms/stopping_criteria/max_iterations_reached.py
paref/moo_algorithms/stopping_criteria/no_pareto_point_was_found.py
paref/moo_algorithms/stopping_criteria/time_limit_reached.py
paref/moo_algorithms/two_dimensional/__init__.py
paref/moo_algorithms/two_dimensional/fill_gaps_of_pareto_front_2d.py
paref/pareto_reflection_sequences/__init__.py
paref/pareto_reflection_sequences/generic/__init__.py
paref/pareto_reflection_sequences/generic/next_when_stopping_criteria_met.py
paref-0.2.0.dist-info/LICENSE.txt
paref-0.2.0.dist-info/METADATA
paref-0.2.0.dist-info/WHEEL
paref-0.2.0.dist-info/top_level.txt
paref-0.2.0.dist-info/RECORD
