Metadata-Version: 2.1
Name: paref
Version: 0.2.0
Summary: Pareto reflection based multi-objective optimization
Author: Nicolai Palm
Author-email: nicolaipalm@googlemail.com
License: MIT
Classifier: Programming Language :: Python :: 3
Classifier: License :: OSI Approved :: MIT License
Classifier: Operating System :: OS Independent
Classifier: Development Status :: 3 - Alpha
Requires-Python: >=3.10
License-File: LICENSE.txt
Requires-Dist: numpy
Requires-Dist: scipy
Requires-Dist: plotly
Requires-Dist: gpytorch
Requires-Dist: torch
Requires-Dist: matplotlib
Requires-Dist: tqdm
Requires-Dist: tabulate
Provides-Extra: dev
Requires-Dist: pre-commit ; extra == 'dev'
Requires-Dist: flake8 ; extra == 'dev'
Requires-Dist: flake8-print ; extra == 'dev'
Provides-Extra: functional_tests
Requires-Dist: ipython ; extra == 'functional_tests'
Requires-Dist: jupyter ; extra == 'functional_tests'
Requires-Dist: pymoo ; extra == 'functional_tests'
Provides-Extra: test
Requires-Dist: pytest ; extra == 'test'
Requires-Dist: pytest-cov ; extra == 'test'
